pyshortner/__init__.py
pyshortner/call.py
pyshortner/main.py
pyshortner-1.0.22.dist-info/LICENSE
pyshortner-1.0.22.dist-info/METADATA
pyshortner-1.0.22.dist-info/WHEEL
pyshortner-1.0.22.dist-info/top_level.txt
pyshortner-1.0.22.dist-info/RECORD
